arl_mcp/__init__.py
arl_mcp/server.py
arl_mcp-0.1.12.dist-info/METADATA
arl_mcp-0.1.12.dist-info/WHEEL
arl_mcp-0.1.12.dist-info/entry_points.txt
arl_mcp-0.1.12.dist-info/RECORD
