Metadata-Version: 2.4
Name: arl-mcp
Version: 0.1.12
Summary: ARL MCP Server - A Model Context Protocol server for ARL platform integration
Project-URL: Homepage, https://github.com/WACHI/arl-mcp
Project-URL: Repository, https://github.com/WACHI/arl-mcp.git
Project-URL: Issues, https://github.com/WACHI/arl-mcp/issues
Author-email: WACHI <wachi@example.com>
Classifier: Development Status :: 3 - Alpha
Classifier: Intended Audience :: Developers
Classifier: License :: OSI Approved :: MIT License
Classifier: Programming Language :: Python :: 3
Classifier: Programming Language :: Python :: 3.8
Classifier: Programming Language :: Python :: 3.9
Classifier: Programming Language :: Python :: 3.10
Classifier: Programming Language :: Python :: 3.11
Classifier: Programming Language :: Python :: 3.12
Requires-Python: >=3.8
Requires-Dist: mcp>=0.1.0
Requires-Dist: requests>=2.25.0
Requires-Dist: tldextract>=3.0.0
Requires-Dist: urllib3>=1.26.0
Provides-Extra: dev
Requires-Dist: black>=21.0; extra == 'dev'
Requires-Dist: flake8>=3.8; extra == 'dev'
Requires-Dist: pytest>=6.0; extra == 'dev'
